pockyt/__init__.py
pockyt/api.py
pockyt/auth.py
pockyt/client.py
pockyt/compat.py
pockyt/pockyt.py
pockyt/wrapper.py
pockyt-1.4.6.dist-info/LICENSE.txt
pockyt-1.4.6.dist-info/METADATA
pockyt-1.4.6.dist-info/WHEEL
pockyt-1.4.6.dist-info/entry_points.txt
pockyt-1.4.6.dist-info/top_level.txt
pockyt-1.4.6.dist-info/RECORD
