Metadata-Version: 2.1
Name: pockyt
Version: 1.4.6
Summary: A simple, yet powerful, commandline client for your Pocket collection.
Home-page: https://github.com/achembarpu/pockyt
Author: Arvind Chembarpu
Author-email: achembarpu@gmail.com
License: GPLv3+
Download-URL: https://github.com/achembarpu/pockyt/tarball/1.4.6
Keywords: pocket,commandline,automation
Platform: UNKNOWN
Classifier: Development Status :: 5 - Production/Stable
Classifier: Environment :: Console
Classifier: Topic :: Utilities
Classifier: Intended Audience :: Developers
Classifier: License :: OSI Approved :: GNU General Public License v3 or later (GPLv3+)
Classifier: Natural Language :: English
Classifier: Operating System :: Microsoft :: Windows
Classifier: Operating System :: POSIX :: Linux
Classifier: Programming Language :: Python :: 2
Classifier: Programming Language :: Python :: 3
Requires-Dist: parse (>=1.19.0)
